{
  "main": {
    "id": "d6c4637d03c9aba2",
    "type": "split",
    "children": [
      {
        "id": "1d1be6ecf055d574",
        "type": "tabs",
        "children": [
          {
            "id": "61ccdd09b08ad042",
            "type": "leaf",
            "state": {
              "type": "markdown",
              "state": {
                "file": "Machine Learning/Stats/Models/6. Neural Network Learning.md",
                "mode": "source",
                "source": false
              }
            }
          },
          {
            "id": "fc48e3864eb4f9ae",
            "type": "leaf",
            "state": {
              "type": "markdown",
              "state": {
                "file": "Machine Learning/Algorithm/6. Support Vector Machine.md",
                "mode": "source",
                "source": false
              }
            }
          }
        ],
        "currentTab": 1
      }
    ],
    "direction": "vertical"
  },
  "left": {
    "id": "e842880b3bac6047",
    "type": "split",
    "children": [
      {
        "id": "7faa162f138bac53",
        "type": "tabs",
        "children": [
          {
            "id": "0e3d9c4c550f9ca9",
            "type": "leaf",
            "state": {
              "type": "file-explorer",
              "state": {
                "sortOrder": "alphabetical"
              }
            }
          },
          {
            "id": "fd15b7c9e49ac477",
            "type": "leaf",
            "state": {
              "type": "search",
              "state": {
                "query": "",
                "matchingCase": false,
                "explainSearch": false,
                "collapseAll": false,
                "extraContext": false,
                "sortOrder": "alphabetical"
              }
            }
          },
          {
            "id": "a16cfca35d6d24dd",
            "type": "leaf",
            "state": {
              "type": "starred",
              "state": {}
            }
          }
        ]
      }
    ],
    "direction": "horizontal",
    "width": 310.5
  },
  "right": {
    "id": "7dcb91c75a3768a3",
    "type": "split",
    "children": [
      {
        "id": "b0573f0c77a254ee",
        "type": "tabs",
        "children": [
          {
            "id": "d8837a168bb7d2e7",
            "type": "leaf",
            "state": {
              "type": "backlink",
              "state": {
                "file": "Machine Learning/Stats/Models/6. Neural Network Learning.md",
                "collapseAll": false,
                "extraContext": false,
                "sortOrder": "alphabetical",
                "showSearch": false,
                "searchQuery": "",
                "backlinkCollapsed": false,
                "unlinkedCollapsed": true
              }
            }
          },
          {
            "id": "99ec26e8c41d3271",
            "type": "leaf",
            "state": {
              "type": "outgoing-link",
              "state": {
                "file": "Machine Learning/Stats/Models/6. Neural Network Learning.md",
                "linksCollapsed": false,
                "unlinkedCollapsed": true
              }
            }
          },
          {
            "id": "6fc3d4e5b474eb74",
            "type": "leaf",
            "state": {
              "type": "tag",
              "state": {
                "sortOrder": "frequency",
                "useHierarchy": true
              }
            }
          },
          {
            "id": "17198e5890d3f845",
            "type": "leaf",
            "state": {
              "type": "outline",
              "state": {
                "file": "Machine Learning/Stats/Models/6. Neural Network Learning.md"
              }
            }
          }
        ],
        "currentTab": 1
      }
    ],
    "direction": "horizontal",
    "width": 200,
    "collapsed": true
  },
  "left-ribbon": {
    "hiddenItems": {
      "switcher:Open quick switcher": false,
      "graph:Open graph view": false,
      "canvas:Create new canvas": false,
      "daily-notes:Open today's daily note": false,
      "templates:Insert template": false,
      "command-palette:Open command palette": false
    }
  },
  "active": "0e3d9c4c550f9ca9",
  "lastOpenFiles": [
    "Wiki.md",
    "Machine Learning/Algorithm/6. Support Vector Machine.md",
    "Data Science/Data Mining/0. Concepts/5. Classification & Prediction/8. SVM, Lazy Learners, & Variants.md",
    "Data Science/Data Mining/2. Algorithm/0. Supervised learning algorithms.md",
    "Data Science/Data Mining/0. Concepts/5. Classification & Prediction/9. Exercises.md",
    "Machine Learning/Stats/Models/6. Neural Network Learning.md",
    "Z-Pictures/Stats-ML/neuralnetworks.png",
    "Z-Pictures/Stats-ML/hidden_unit.png",
    "Z-Pictures/Stats-ML/Multi.png",
    "Statistics/1. Statistical Inference/3. Neural Network/0. Neural Network Learning.md",
    "Data Science/Data Mining/0. Concepts/5. Classification & Prediction/7. Linear Regression & Neural Nets.md",
    "Data Science/Data Mining/0. Concepts/5. Classification & Prediction/6. Evaluation of Classifiers.md",
    "Statistics/1. Statistical Inference/2. Regression/0. Linear Regression.md",
    "Machine Learning/Algorithm/7. Convolutional neural networks.md",
    "Machine Learning/Stats/Models/5.  Logistic Regression.md",
    "Statistics/1. Statistical Inference/3. Neural Network",
    "Machine Learning/Algorithm/1. Linear Regression.md",
    "Python/Flask/0. Start.md",
    "Python/Flask/1. URL and View Mapping.md",
    "Python/Flask",
    "Data Science/Data Mining/0. Concepts/5. Classification & Prediction/5. Bayes Classifiers.md",
    "Data Science/Data Mining/0. Concepts/6. Classification",
    "conflict-files-obsidian-git.md",
    "Symbolic AI/3. KRR/3. CSP.md",
    "Computer Vision/0. Image Processing.md",
    "Computer Vision",
    "Computer Networking/3. Data Link Layer/Untitled.md",
    "Computer Networking/3. Data Link Layer",
    "Computer Networking/2. Physical Layer/3. Nyquist Theorem.md",
    "Computer Networking/2. Physical Layer/2. Symbol.md",
    "Computer Networking/2. Physical Layer/1. The Physical Layer.md",
    "Computer Networking/2. Physical Layer",
    "Computer Networking/1. Overview/3. Network Latency and Performance.md",
    "Data Science/Data Mining/0. Concepts/5. Classification & Prediction/4. Rule-Based Classification.md",
    "Data Science/Data Mining/0. Concepts/5. Classification & Prediction/3. Enhancements to the Basic Algorithm.md",
    "Untitled 1.canvas",
    "Untitled.canvas",
    "Data Science/Data Mining/0. Concepts/5. Classification & Prediction",
    "Symbolic AI/3. KRR/2. Prenex",
    "Data Science/Data Mining/3. Classification & Prediction",
    "Z-Pictures/AI/Screen Shot 2023-03-25 at 8.27.49 pm.png",
    "Z-Pictures/AI/search.png",
    "Z-Pictures/AI/Screen Shot 2023-03-25 at 7.22.47 pm.png",
    "Z-Pictures/AI",
    "Z-Pictures/Data/cuboids cal.png",
    "Z-Pictures/Data/data cube 1.png",
    "Z-Pictures/Data/data warehouse pivot.png",
    "Z-Pictures/Data/data cube.png"
  ]
}